django_activeurl/__about__.py
django_activeurl/__init__.py
django_activeurl/conf.py
django_activeurl/models.py
django_activeurl/utils.py
django_activeurl/ext/__init__.py
django_activeurl/ext/django_jinja.py
django_activeurl/templatetags/__init__.py
django_activeurl/templatetags/activeurl.py
django_activeurl-0.1.12.dist-info/DESCRIPTION.rst
django_activeurl-0.1.12.dist-info/LICENSE.txt
django_activeurl-0.1.12.dist-info/METADATA
django_activeurl-0.1.12.dist-info/RECORD
django_activeurl-0.1.12.dist-info/WHEEL
django_activeurl-0.1.12.dist-info/metadata.json
django_activeurl-0.1.12.dist-info/top_level.txt
