Metadata-Version: 2.0
Name: django-activeurl
Version: 0.1.12
Summary: Easy-to-use active URL highlighting for Django
Home-page: https://github.com/hellysmile/django-activeurl/
Author: hellysmile
Author-email: hellysmile@gmail.com
License: Apache 2.0
Download-URL: https://pypi.python.org/pypi/django-activeurl
Keywords: django,url,link,active,css,templatetag,jinja2
Platform: UNKNOWN
Classifier: Framework :: Django
Classifier: Environment :: Web Environment
Classifier: Intended Audience :: Developers
Classifier: Topic :: Internet :: WWW/HTTP
Classifier: License :: OSI Approved :: Apache Software License
Classifier: Development Status :: 5 - Production/Stable
Classifier: Natural Language :: English
Classifier: Programming Language :: Python
Classifier: Programming Language :: Python :: 2
Classifier: Programming Language :: Python :: 2.7
Classifier: Programming Language :: Python :: 3
Classifier: Programming Language :: Python :: 3.4
Classifier: Programming Language :: Python :: 3.5
Classifier: Programming Language :: Python :: 3.6
Classifier: Programming Language :: Python :: Implementation :: CPython
Classifier: Programming Language :: Python :: Implementation :: PyPy
Classifier: Operating System :: MacOS :: MacOS X
Classifier: Operating System :: Microsoft :: Windows
Classifier: Operating System :: POSIX
Classifier: Operating System :: Unix
Requires-Dist: django
Requires-Dist: lxml
Requires-Dist: django-classy-tags
Requires-Dist: django-appconf
